adafruit_mpr121.py
adafruit_circuitpython_mpr121-2.1.22.dist-info/LICENSE
adafruit_circuitpython_mpr121-2.1.22.dist-info/METADATA
adafruit_circuitpython_mpr121-2.1.22.dist-info/WHEEL
adafruit_circuitpython_mpr121-2.1.22.dist-info/top_level.txt
adafruit_circuitpython_mpr121-2.1.22.dist-info/RECORD
