Metadata-Version: 2.2
Name: adafruit-circuitpython-mpr121
Version: 2.1.22
Summary: CircuitPython library for MPR121 capacitive touch breakout board.
Author-email: Adafruit Industries <circuitpython@adafruit.com>
License: MIT
Project-URL: Homepage, https://github.com/adafruit/Adafruit_CircuitPython_MPR121
Keywords: adafruit,mpr121,capacitive,touch,breakout,hardware,micropython,circuitpython
Classifier: Intended Audience :: Developers
Classifier: Topic :: Software Development :: Libraries
Classifier: Topic :: Software Development :: Embedded Systems
Classifier: Topic :: System :: Hardware
Classifier: License :: OSI Approved :: MIT License
Classifier: Programming Language :: Python :: 3
License-File: LICENSE
Requires-Dist: Adafruit-Blinka
Requires-Dist: adafruit-circuitpython-busdevice>=2.2.5
Provides-Extra: optional
